LICENSE
build.py
tid-0.2.0.dist-info/RECORD
tid-0.2.0.dist-info/LICENSE
tid-0.2.0.dist-info/WHEEL
tid-0.2.0.dist-info/METADATA
tid/.gitignore
tid/_gettid.pyx
tid/_gettid.cpython-37m-x86_64-linux-gnu.so
tid/__init__.py
tid/_gettid.c
